safex/__init__.py
safex/eval.py
safex-0.7.0.dist-info/WHEEL
safex-0.7.0.dist-info/METADATA
safex-0.7.0.dist-info/RECORD
