Metadata-Version: 2.1
Name: safex
Version: 0.7.0
Summary: Simple and safe expression evaluator
Home-page: https://github.com/rahulkmr/safex
License: MIT
Author: Rahul Kumar
Author-email: r@thoughtnirvana.com
Requires-Python: >=3.7,<4.0
Classifier: License :: OSI Approved :: MIT License
Classifier: Programming Language :: Python :: 3
Classifier: Programming Language :: Python :: 3.10
Classifier: Programming Language :: Python :: 3.7
Classifier: Programming Language :: Python :: 3.8
Classifier: Programming Language :: Python :: 3.9
Project-URL: Repository, https://github.com/rahulkmr/safex
